storjrpcudp/__init__.py
storjrpcudp/exceptions.py
storjrpcudp/protocol.py
rpcudp/__init__.py
rpcudp/exceptions.py
rpcudp/protocol.py
storjrpcudp-2.5.dist-info/DESCRIPTION.rst
storjrpcudp-2.5.dist-info/metadata.json
storjrpcudp-2.5.dist-info/METADATA
storjrpcudp-2.5.dist-info/WHEEL
storjrpcudp-2.5.dist-info/top_level.txt
storjrpcudp-2.5.dist-info/RECORD
