Metadata-Version: 2.0
Name: storjrpcudp
Version: 2.5
Summary: RPC via UDP
Home-page: https://github.com/Storj/storjrpcudp
Author: Brian Muller
Author-email: bamuller@gmail.com
License: MIT
Platform: UNKNOWN
Requires: twisted.internet.protocol.DatagramProtocol
Requires: umsgpack
Requires: future
Requires-Dist: twisted (>=12.0)
Requires-Dist: u-msgpack-python (>=1.5)
Requires-Dist: future (>=0.6)
